adder4.sv
`timescale 1ns / 1ps

module adder4 (

    input logic clk,
    input logic [3:0] a,
    input logic [3:0] b,
    output logic [4:0] sum
);


always_ff @(negedge clk) begin
    
    sum <= a + b;

end

endmodule

tb_adder4.sv
`timescale 1ns/1ps

module tb_adder4 ();

  // DUT interface signals
  logic        clk;
  logic [3:0]  a, b;
  logic [4:0]  sum;

  // Instantiate DUT (ensure your DUT module is really named 'adder4')
  adder4 uut (
    .clk(clk),
    .a  (a),
    .b  (b),
    .sum(sum)
  );

  // 10 ns Clock Period
  initial clk = 0;
  always  #5 clk = ~clk;

  // Wave dump
  initial begin
    $dumpfile("tb_adder4.vcd");
    $dumpvars(0, tb_adder4);
  end

  // Counters (use 'integer' for broad tool compatibility)
  integer test_cnt = 0;
  integer pass_cnt = 0;
  integer fail_cnt = 0;

  // Drive before edge; check on posedge (registered DUT)
  // NOTE: avoid 'logic' in task ports for Icarus compatibility
  task automatic do_check(input [3:0] aa, input [3:0] bb);
    logic [4:0] exp;           // no 'automatic' on local var — not needed
    @(negedge clk);            // drive on safe phase
    a = aa;
    b = bb;
    exp = aa + bb;

    @(posedge clk);            // sample on registered output edge
    test_cnt = test_cnt + 1;
    if (sum === exp) begin
      pass_cnt = pass_cnt + 1;
      $display("RESULT,PASS,%0d,%0d,%0d,%0d", a, b, sum, exp);
    end
    else begin
      fail_cnt = fail_cnt + 1;
      $display("RESULT,FAIL,%0d,%0d,%0d,%0d", a, b, sum, exp);
    end
  endtask

  // === Test Sequence ===
  initial begin
    a = '0;
    b = '0;

    // Directed vectors
    do_check(4'd0,  4'd0);
    do_check(4'd3,  4'd5);
    do_check(4'd15, 4'd1);
    do_check(4'd8,  4'd7);

    // Randomized smoke (use modulo for wide compatibility)
    repeat (20) do_check($urandom % 16, $urandom % 16);

    // Summary for CI/Jenkins
    $display("SUMMARY,TESTS,%0d,PASS,%0d,FAIL,%0d", test_cnt, pass_cnt, fail_cnt);

    if (fail_cnt != 0) $fatal(1, "Testbench reported %0d failures", fail_cnt);

    $finish;
  end

endmodule

tb_adder4.vcd
$date
	Sun Sep 14 13:09:36 2025
$end
$version
	Icarus Verilog
$end
$timescale
	1ps
$end
$scope module tb_adder4 $end
$var wire 5 ! sum [4:0] $end
$var reg 4 " a [3:0] $end
$var reg 4 # b [3:0] $end
$var reg 1 $ clk $end
$var integer 32 % fail_cnt [31:0] $end
$var integer 32 & pass_cnt [31:0] $end
$var integer 32 ' test_cnt [31:0] $end
$scope module uut $end
$var wire 4 ( a [3:0] $end
$var wire 4 ) b [3:0] $end
$var wire 1 $ clk $end
$var reg 5 * sum [4:0] $end
$upscope $end
$scope task do_check $end
$upscope $end
$upscope $end
$enddefinitions $end
$comment Show the parameter values. $end
$dumpall
$end
#0
$dumpvars
b0 *
b0 )
b0 (
b0 '
b0 &
b0 %
0$
b0 #
b0 "
b0 !
$end
#5000
1$
#10000
0$
#15000
b1 &
b1 '
1$
#20000
b1000 !
b1000 *
b101 #
b101 )
b11 "
b11 (
0$
#25000
b10 &
b10 '
1$
#30000
b10000 !
b10000 *
b1 #
b1 )
b1111 "
b1111 (
0$
#35000
b11 &
b11 '
1$
#40000
b1111 !
b1111 *
b111 #
b111 )
b1000 "
b1000 (
0$
#45000
b100 &
b100 '
1$
#50000
b101 !
b101 *
b1 #
b1 )
b100 "
b100 (
0$
#55000
b101 &
b101 '
1$
#60000
b1100 !
b1100 *
b11 #
b11 )
b1001 "
b1001 (
0$
#65000
b110 &
b110 '
1$
#70000
b11010 !
b11010 *
b1101 #
b1101 )
b1101 "
b1101 (
0$
#75000
b111 &
b111 '
1$
#80000
b111 !
b111 *
b10 #
b10 )
b101 "
b101 (
0$
#85000
b1000 &
b1000 '
1$
#90000
b1110 !
b1110 *
b1101 #
b1101 )
b1 "
b1 (
0$
#95000
b1001 &
b1001 '
1$
#100000
b10011 !
b10011 *
b110 "
b110 (
0$
#105000
b1010 &
b1010 '
1$
#110000
b11001 !
b11001 *
b1100 #
b1100 )
b1101 "
b1101 (
0$
#115000
b1011 &
b1011 '
1$
#120000
b1111 !
b1111 *
b110 #
b110 )
b1001 "
b1001 (
0$
#125000
b1100 &
b1100 '
1$
#130000
b1010 #
b1010 )
b101 "
b101 (
0$
#135000
b1101 &
b1101 '
1$
#140000
b1100 !
b1100 *
b111 #
b111 )
0$
#145000
b1110 &
b1110 '
1$
#150000
b10001 !
b10001 *
b1111 #
b1111 )
b10 "
b10 (
0$
#155000
b1111 &
b1111 '
1$
#160000
b10000 !
b10000 *
b1110 #
b1110 )
0$
#165000
b10000 &
b10000 '
1$
#170000
b1101 !
b1101 *
b101 #
b101 )
b1000 "
b1000 (
0$
#175000
b10001 &
b10001 '
1$
#180000
b11001 !
b11001 *
b1101 #
b1101 )
b1100 "
b1100 (
0$
#185000
b10010 &
b10010 '
1$
#190000
b10010 !
b10010 *
b101 #
b101 )
b1101 "
b1101 (
0$
#195000
b10011 &
b10011 '
1$
#200000
b1101 !
b1101 *
b1010 #
b1010 )
b11 "
b11 (
0$
#205000
b10100 &
b10100 '
1$
#210000
b0 !
b0 *
b0 #
b0 )
b0 "
b0 (
0$
#215000
b10101 &
b10101 '
1$
#220000
b10111 !
b10111 *
b1101 #
b1101 )
b1010 "
b1010 (
0$
#225000
b10110 &
b10110 '
1$
#230000
b1001 !
b1001 *
b11 #
b11 )
b110 "
b110 (
0$
#235000
b10111 &
b10111 '
1$
#240000
b10000 !
b10000 *
b1101 "
b1101 (
0$
#245000
b11000 &
b11000 '
1$
